{
  "recentFiles": [
    {
      "basename": "hello-world",
      "path": "source/_posts/hello-world.md"
    },
    {
      "basename": "未命名看板",
      "path": "未命名看板.md"
    },
    {
      "basename": "Drawing 2026-02-07 15.37.12.excalidraw",
      "path": "Excalidraw/Drawing 2026-02-07 15.37.12.excalidraw.md"
    },
    {
      "basename": "2026-01-17-Disboundia-开发日志",
      "path": "source/_posts/2026-01-17-Disboundia-开发日志.md"
    },
    {
      "basename": "2026-01-16-Disboundia-开发日志",
      "path": "source/_posts/2026-01-16-Disboundia-开发日志.md"
    },
    {
      "basename": "AI 3D Model",
      "path": "AI 3D Model.md"
    },
    {
      "basename": "AI 工具",
      "path": "AI 工具.md"
    },
    {
      "basename": "Drawing 2026-02-06 16.22.04.excalidraw",
      "path": "Excalidraw/Drawing 2026-02-06 16.22.04.excalidraw.md"
    },
    {
      "basename": "hello-world",
      "path": "Blog/source/_posts/hello-world.md"
    },
    {
      "basename": "Untitled 1",
      "path": "Untitled 1.canvas"
    },
    {
      "basename": "2026-01-18-Disboundia-开发日志",
      "path": "Blog/source/_posts/2026-01-18-Disboundia-开发日志.md"
    },
    {
      "basename": "Drawing 2026-02-06 19.26.11.excalidraw",
      "path": "Excalidraw/Drawing 2026-02-06 19.26.11.excalidraw.md"
    },
    {
      "basename": "README",
      "path": "Blog/node_modules/highlight.js/README.md"
    },
    {
      "basename": "license",
      "path": "Blog/node_modules/ms/license.md"
    },
    {
      "basename": "未命名",
      "path": "未命名.canvas"
    },
    {
      "basename": "工作",
      "path": "工作.md"
    },
    {
      "basename": "create a link",
      "path": "create a link.md"
    },
    {
      "basename": "2026-W06",
      "path": "2026-W06.md"
    },
    {
      "basename": "未命名 2",
      "path": "未命名 2.md"
    },
    {
      "basename": "Untitled Kanban",
      "path": "Untitled Kanban.md"
    },
    {
      "basename": "未命名 1",
      "path": "未命名 1.md"
    },
    {
      "basename": "2026-02-06",
      "path": "2026-02-06.md"
    },
    {
      "basename": "Untitled 1",
      "path": "Untitled 1.md"
    },
    {
      "basename": "Untitled",
      "path": "Untitled.md"
    },
    {
      "basename": "Untitled",
      "path": "Untitled.canvas"
    },
    {
      "basename": "Untitled Kanban 1",
      "path": "Untitled Kanban 1.md"
    }
  ],
  "omittedPaths": [],
  "omittedTags": [],
  "updateOn": "file-open",
  "omitBookmarks": false
}